Blockporn/__init__.py
Blockporn/module.py
Blockporn/scripts.py
Blockporn/RECORDED/blocked.txt
blockporn-0.1.6.dist-info/licenses/LICENSE
blockporn-0.1.6.dist-info/METADATA
blockporn-0.1.6.dist-info/WHEEL
blockporn-0.1.6.dist-info/top_level.txt
blockporn-0.1.6.dist-info/RECORD
